kaquel/__init__.py
kaquel/errors.py
kaquel/es_query.py
kaquel/kql.py
kaquel/lucene.py
kaquel/py.typed
kaquel/query.py
kaquel/utils.py
kaquel-0.3.1.dist-info/LICENSE.txt
kaquel-0.3.1.dist-info/METADATA
kaquel-0.3.1.dist-info/WHEEL
kaquel-0.3.1.dist-info/RECORD
