Metadata-Version: 2.1
Name: kaquel
Version: 0.3.1
Summary: Tools for handling ElasticSearch queries in various languages
Home-page: https://kaquel.touhey.pro/
Keywords: elasticsearch,es_query,es-query,kibana,kql,lucene,parsing,query
Author: Thomas Touhey
Author-email: thomas@touhey.fr
Requires-Python: >=3.9,<4.0
Classifier: Development Status :: 4 - Beta
Classifier: Intended Audience :: Developers
Classifier: Intended Audience :: System Administrators
Classifier: License :: CeCILL-C Free Software License Agreement (CECILL-C)
Classifier: Natural Language :: English
Classifier: Programming Language :: Python :: 3
Classifier: Programming Language :: Python :: 3.9
Classifier: Programming Language :: Python :: 3.10
Classifier: Programming Language :: Python :: 3.11
Classifier: Programming Language :: Python :: 3.12
Classifier: Programming Language :: Python :: 3 :: Only
Classifier: Topic :: Database :: Front-Ends
Classifier: Typing :: Typed
Requires-Dist: eval-type-backport (>=0.2,<0.3) ; python_version < "3.10"
Requires-Dist: pydantic (>=2.7.1,<3.0.0)
Project-URL: Repository, https://gitlab.com/kaquel/kaquel
